p1/mux4_1.v
//objetivo 1     mux 4_1_v
///como usa reg hay q usar bloquees tipo initial y always
///modelado de comporatmiento

module mux4_1(output reg out, input wire a, b, c, d, input wire [1:0] s);

always@(a,b,c,d,s)           // cuandondo cambie alguno de esos ejecuta codigo

begin   
case(s)

2'b00:out = a;              // si lleva mas de una linea hay q usar begin and end
2'b01:out = b;
2'b10:out = c;
2'b11:out = d;
default:out = 1'bX;         // caso inprevisto

endcase
end
endmodule

/// _nbits"_base_valor    notacion
///iverilog mux4_1v:

p1/mux4_1_tb.v
// Testbench para modulo de multiplexor module mux4_1(output reg out, input wire a, b, c, d, input wire [1:0] s);
`timescale 1 ns / 10 ps //Directiva que fija la unidad de tiempo de simulación y el paso de simulación

module mux4_1_tb;
//declaracion de señales
wire test_out;
reg test_a, test_b, test_c, test_d; 
reg [1:0] test_s;

mux4_1 mux1(test_out, test_a, test_b, test_c, test_d, test_s);

initial
begin
  $monitor("tiempo=%0d a=%b b=%b c=%b d=%b s=%b out=%b", $time, test_a, test_b,test_c, test_d,test_s, test_out );
  $dumpfile("mux4_1_tb.vcd");
  $dumpvars;

 test_s = 2'b00;
 test_a = 1'b0;
 #20;

 test_s = 2'b00;
 test_a = 1'b1;
 #20;

 test_s = 2'b01;
 test_b = 1'b0;
 #20;

 test_s = 2'b01;
 test_b = 1'b1;
 #20;

 test_s = 2'b10;
 test_c = 1'b0;
 #20;

 test_s = 2'b10;
 test_c = 1'b1;
 #20;

 test_s = 2'b11;
 test_d = 1'b0;
 #20;

 test_s = 2'b11;
 test_d = 1'b1;
 #20;

 $finish;

end
endmodule

p1/mux4_1_tb.vcd
$date
	Mon Nov  2 17:40:42 2020
$end
$version
	Icarus Verilog
$end
$timescale
	10ps
$end
$scope module mux4_1_tb $end
$var wire 1 ! test_out $end
$var reg 1 " test_a $end
$var reg 1 # test_b $end
$var reg 1 $ test_c $end
$var reg 1 % test_d $end
$var reg 2 & test_s [1:0] $end
$scope module mux1 $end
$var wire 1 " a $end
$var wire 1 # b $end
$var wire 1 $ c $end
$var wire 1 % d $end
$var wire 2 ' s [1:0] $end
$var reg 1 ! out $end
$upscope $end
$upscope $end
$enddefinitions $end
#0
$dumpvars
b0 '
b0 &
x%
x$
x#
0"
0!
$end
#2000
1!
1"
#4000
0!
0#
b1 &
b1 '
#6000
1!
1#
#8000
0!
0$
b10 &
b10 '
#10000
1!
1$
#12000
0!
0%
b11 &
b11 '
#14000
1!
1%
